modernmt/__init__.py
modernmt/modernmt.py
modernmt-1.5.2.dist-info/LICENSE
modernmt-1.5.2.dist-info/METADATA
modernmt-1.5.2.dist-info/WHEEL
modernmt-1.5.2.dist-info/top_level.txt
modernmt-1.5.2.dist-info/RECORD
