Metadata-Version: 2.1
Name: modernmt
Version: 1.5.2
Summary: ModernMT API wrapper
Home-page: https://github.com/modernmt/modernmt-python
Author: ModernMT
Author-email: info@modernmt.com
Project-URL: Bug Tracker, https://github.com/modernmt/modernmt-python/issues
Classifier: Programming Language :: Python :: 3
Classifier: License :: OSI Approved :: MIT License
Classifier: Operating System :: OS Independent
Requires-Python: >=3
License-File: LICENSE
Requires-Dist: requests
Requires-Dist: pyjwt
